service_config_foundry/__init__.py
service_config_foundry/config_parser.py
service_config_foundry/file_type.py
service_config_foundry/service.py
service_config_foundry/service_location.py
service_config_foundry/utils.py
service_config_foundry/sections/__init__.py
service_config_foundry/sections/automount.py
service_config_foundry/sections/install.py
service_config_foundry/sections/mount.py
service_config_foundry/sections/path.py
service_config_foundry/sections/scope.py
service_config_foundry/sections/service.py
service_config_foundry/sections/slice.py
service_config_foundry/sections/socket.py
service_config_foundry/sections/swap.py
service_config_foundry/sections/timer.py
service_config_foundry/sections/unit.py
service_config_foundry-0.5.4.dist-info/licenses/LICENSE
service_config_foundry-0.5.4.dist-info/METADATA
service_config_foundry-0.5.4.dist-info/WHEEL
service_config_foundry-0.5.4.dist-info/top_level.txt
service_config_foundry-0.5.4.dist-info/RECORD
