Metadata-Version: 2.4
Name: service_config_foundry
Version: 0.5.4
Summary: Helps create non-templated systemd services.
Home-page: https://github.com/yushdotkapoor/service-config-foundry
Author: Yush Kapoor
Author-email: Yush Kapoor <yushdotkapoor@gmail.com>
License: MIT
Project-URL: Homepage, https://github.com/yushdotkapoor/service_config_foundry
Project-URL: Repository, https://github.com/yushdotkapoor/service_config_foundry
Project-URL: Bug Tracker, https://github.com/yushdotkapoor/service_config_foundry/issues
Keywords: systemd,service,linux,system-administration
Classifier: Programming Language :: Python :: 3
Classifier: Programming Language :: Python :: 3.8
Classifier: Programming Language :: Python :: 3.9
Classifier: Programming Language :: Python :: 3.10
Classifier: Programming Language :: Python :: 3.11
Classifier: Programming Language :: Python :: 3.12
Classifier: License :: OSI Approved :: MIT License
Classifier: Operating System :: OS Independent
Classifier: Intended Audience :: Developers
Classifier: Topic :: System :: Systems Administration
Classifier: Topic :: Software Development :: Libraries :: Python Modules
Requires-Python: >=3.8
License-File: LICENSE
Provides-Extra: test
Requires-Dist: pytest>=7.0.0; extra == "test"
Requires-Dist: pytest-mock>=3.10.0; extra == "test"
Requires-Dist: pytest-cov>=4.0.0; extra == "test"
Requires-Dist: flake8>=6.0.0; extra == "test"
Requires-Dist: black>=23.0.0; extra == "test"
Requires-Dist: isort>=5.12.0; extra == "test"
Provides-Extra: dev
Requires-Dist: pytest>=7.0.0; extra == "dev"
Requires-Dist: pytest-mock>=3.10.0; extra == "dev"
Requires-Dist: pytest-cov>=4.0.0; extra == "dev"
Requires-Dist: flake8>=6.0.0; extra == "dev"
Requires-Dist: black>=23.0.0; extra == "dev"
Requires-Dist: isort>=5.12.0; extra == "dev"
Requires-Dist: pre-commit>=3.0.0; extra == "dev"
Requires-Dist: tox>=4.0.0; extra == "dev"
Requires-Dist: twine>=4.0.0; extra == "dev"
Requires-Dist: build>=0.10.0; extra == "dev"
Requires-Dist: bump2version>=1.0.0; extra == "dev"
Dynamic: author
Dynamic: home-page
Dynamic: license-file
Dynamic: requires-python
